CHANGELOG.txt
LICENSE.txt
MANIFEST.in
README.rst
setup.py
test.py
test_interp.py
test_mde.py
test_quadrature.py
chebpy/__init__.py
chebpy/cheb.py
chebpy/cheba.py
chebpy/chebd.py
chebpy/chebi.py
chebpy/chebq.py
chebpy/chebt.py
chebpy/integral.py
chebpy/misc.py
chebpy.egg-info/PKG-INFO
chebpy.egg-info/SOURCES.txt
chebpy.egg-info/dependency_links.txt
chebpy.egg-info/not-zip-safe
chebpy.egg-info/requires.txt
chebpy.egg-info/top_level.txt