Metadata-Version: 1.0
Name: chebpy
Version: 0.2
Summary: Chebyshev polynomial based spectral methods of PDEs.
Home-page: https://bitbucket.org/liuyxpp/chebpy
Author: Yi-Xin Liu
Author-email: liuyxpp@gmail.com
License: BSD
Platform: UNKNOWN
Classifier: Development Status :: 4 - Beta
Classifier: Intended Audience :: Science/Research
Classifier: Intended Audience :: Developers
Classifier: Intended Audience :: Education
Classifier: License :: OSI Approved :: BSD License
Classifier: Operating System :: POSIX :: Linux
Classifier: Programming Language :: Python
Classifier: Topic :: Scientific/Engineering
Classifier: Topic :: Education
